async_clash/__init__.py
async_clash/auth.py
async_clash/config.py
async_clash/proxy.py
async_clash-0.0.2.dist-info/METADATA
async_clash-0.0.2.dist-info/WHEEL
async_clash-0.0.2.dist-info/licenses/LICENSE
async_clash-0.0.2.dist-info/RECORD
